integration_test_plugin/__init__.py
integration_test_plugin/path_verifier.py
integration_test_plugin/process_verifier.py
integration_test_plugin/stream_verifier.py
integration_test_plugin-1.0.0.dist-info/METADATA
integration_test_plugin-1.0.0.dist-info/WHEEL
integration_test_plugin-1.0.0.dist-info/top_level.txt
integration_test_plugin-1.0.0.dist-info/RECORD
