Metadata-Version: 2.1
Name: integration-test-plugin
Version: 1.0.0
Summary: A plugin which enable testing of target executables on Python3 unittest framework.
Home-page: https://github.com/Bacondish2023/integration_test_plugin
Author: Hidekazu TAKAHASHI
Author-email: 139677991+Bacondish2023@users.noreply.github.com
License: MIT License
Keywords: development testing-tool
Platform: UNKNOWN
Classifier: Topic :: Software Development :: Testing
Classifier: Intended Audience :: Developers
Classifier: License :: OSI Approved :: MIT License
Classifier: Programming Language :: Python :: 3.6
Classifier: Programming Language :: Python :: 3.7
Classifier: Programming Language :: Python :: 3.8
Classifier: Programming Language :: Python :: 3.9
Classifier: Programming Language :: Python :: 3.10
Classifier: Programming Language :: Python :: 3.11
Requires-Python: >=3.6
